mypackage/__init__.py
mypackage/__version__.py
mypackage/core.py
ldshell-1.6.0.dist-info/LICENSE
ldshell-1.6.0.dist-info/METADATA
ldshell-1.6.0.dist-info/WHEEL
ldshell-1.6.0.dist-info/top_level.txt
ldshell-1.6.0.dist-info/RECORD
